youtube_easy_api/easy_wrapper.py
youtube_easy_api/test_easy_wrapper.py
youtube_easy_api-0.2.2.dist-info/LICENSE.md
youtube_easy_api-0.2.2.dist-info/METADATA
youtube_easy_api-0.2.2.dist-info/WHEEL
youtube_easy_api-0.2.2.dist-info/entry_points.txt
youtube_easy_api-0.2.2.dist-info/top_level.txt
youtube_easy_api-0.2.2.dist-info/RECORD
