Metadata-Version: 2.1
Name: youtube-easy-api
Version: 0.2.2
Summary: How to search among Youtube videos and extract their metadata using an easy interface.
Home-page: https://github.com/pdrm83/youtube_api_wrapper
Author: Pedram Ataee
Author-email: pedram.ataee@gmail.com
License: MIT
Platform: UNKNOWN
Classifier: License :: OSI Approved :: MIT License
Classifier: Programming Language :: Python :: 3
Classifier: Programming Language :: Python :: 3.7
Requires-Dist: google-api-python-client
Requires-Dist: google-auth-oauthlib
Requires-Dist: google
